praktikum/__init__.py
praktikum/analyse.py
praktikum/cassy.py
praktikum/cassy1.py
praktikum/cassy_tools.py
praktikum/literaturwerte.py
praktikum/data/Wasser_Dichte.csv
praktikum/data/Wasser_NIST.csv
praktikum/data/__init__.py
praktikum-2.7.1.dist-info/licenses/LICENSE
praktikum-2.7.1.dist-info/METADATA
praktikum-2.7.1.dist-info/WHEEL
praktikum-2.7.1.dist-info/entry_points.txt
praktikum-2.7.1.dist-info/top_level.txt
praktikum-2.7.1.dist-info/RECORD
